opensr_mamba/__init__.py
opensr_mamba/main.py
opensr_mamba/mamba/attention.py
opensr_mamba/mamba/main.py
opensr_mamba/mamba/model.py
opensr_mamba/mamba/patchify.py
opensr_mamba/mamba/upsample.py
opensr_mamba/mamba/weights/fusionmodel01.pth
opensr_mamba/mamba/weights/fusionmodel02.pth
opensr_mamba/mamba/weights/srmodel.pth
opensr_mamba-0.0.1.dist-info/LICENSE
opensr_mamba-0.0.1.dist-info/METADATA
opensr_mamba-0.0.1.dist-info/WHEEL
opensr_mamba-0.0.1.dist-info/RECORD
