Metadata-Version: 2.1
Name: opensr_mamba
Version: 0.0.1
Summary: A python package to super-resolve Sentinel-2 imagery
Home-page: https://github.com/csaybar/opensr-mamba
Author: Cesar Aybar
Author-email: fcesar.aybar@uv.es
Requires-Python: >=3.8,<4.0
Classifier: Programming Language :: Python :: 3
Classifier: Programming Language :: Python :: 3.8
Classifier: Programming Language :: Python :: 3.9
Classifier: Programming Language :: Python :: 3.10
Classifier: Programming Language :: Python :: 3.11
Classifier: Programming Language :: Python :: 3.12
Requires-Dist: einops (>=0.8.0)
Requires-Dist: mamba-ssm (>=2.2.2)
Requires-Dist: timm (>=1.0.9)
Requires-Dist: torch (>=2.2.0)
Project-URL: Documentation, https://csaybar.github.io/opensr-mamba/
Project-URL: Repository, https://github.com/csaybar/opensr-mamba
